{"Nodes":[],"ExecutionTime":"2022-04-27T11:53:38.5633709Z","GenerationTime":"0001-01-01T00:00:00","PluginUserSpecFlowId":"1e3c4430-04cb-4098-8846-7fee4a82ffd0","CLIUserSpecFlowId":null,"ExecutionResults":[{"ContextType":"Scenario","FeatureFolderPath":"Features/Selenium","FeatureTitle":"TC01_DriverNavigation","ScenarioTitle":"[Moving driver to a website]","ScenarioArguments":[],"Status":"OK","StepResults":[{"Duration":"00:00:00.0001853","Status":"OK","Error":null,"Outputs":null},{"Duration":"00:00:00.5479291","Status":"OK","Error":null,"Outputs":null},{"Duration":"00:00:00.0667391","Status":"OK","Error":null,"Outputs":null}],"Outputs":null}],"StepReports":null}